CHANGELOG.rst
rake_nltk/__init__.py
rake_nltk/__version__.py
rake_nltk/rake.py
rake_nltk-1.0.5.dist-info/LICENSE
rake_nltk-1.0.5.dist-info/WHEEL
rake_nltk-1.0.5.dist-info/METADATA
rake_nltk-1.0.5.dist-info/RECORD
