Metadata-Version: 2.1
Name: rake-nltk
Version: 1.0.5
Summary: RAKE short for Rapid Automatic Keyword Extraction algorithm, is a domain independent keyword extraction algorithm which tries to determine key phrases in a body of text by analyzing the frequency of word appearance and its co-occurance with other words in the text.
Home-page: https://csurfer.github.io/rake-nltk
License: MIT
Keywords: nlp,text-mining,algorithms,development
Author: csurfer
Author-email: sharma.vishwas88@gmail.com
Requires-Python: >=3.6,<4.0
Classifier: Development Status :: 3 - Alpha
Classifier: Intended Audience :: Developers
Classifier: Intended Audience :: Education
Classifier: License :: OSI Approved :: MIT License
Classifier: Operating System :: POSIX
Classifier: Programming Language :: Python :: 3
Classifier: Programming Language :: Python :: 3.6
Classifier: Programming Language :: Python :: 3.7
Classifier: Programming Language :: Python :: 3.8
Classifier: Programming Language :: Python :: 3.9
Classifier: Topic :: Software Development :: Build Tools
Classifier: Topic :: Software Development :: Libraries :: Python Modules
Requires-Dist: nltk (>=3.6.2,<4.0.0)
Project-URL: Repository, https://github.com/csurfer/rake-nltk
